jsonl2htmlmd/__init__.py
jsonl2htmlmd/cli.py
jsonl2htmlmd-0.1.0.dist-info/licenses/LICENSE
jsonl2htmlmd-0.1.0.dist-info/METADATA
jsonl2htmlmd-0.1.0.dist-info/WHEEL
jsonl2htmlmd-0.1.0.dist-info/entry_points.txt
jsonl2htmlmd-0.1.0.dist-info/top_level.txt
jsonl2htmlmd-0.1.0.dist-info/RECORD
