Metadata-Version: 2.4
Name: jsonl2htmlmd
Version: 0.1.0
Summary: Convert JSONL files into HTML tables with full Markdown rendering support
Author-email: BrookJI <lllabmaster@gmail.com>
License: MIT
Keywords: jsonl,markdown,html,datatable,viewer,llm,dataset
Requires-Python: >=3.8
License-File: LICENSE
Dynamic: license-file
